atlas_consortia_clt/__init__.py
atlas_consortia_clt/__version__.py
atlas_consortia_clt/common/__init__.py
atlas_consortia_clt/common/app.cfg
atlas_consortia_clt/common/config.py
atlas_consortia_clt/common/help.py
atlas_consortia_clt/common/main.py
atlas_consortia_clt/hubmap_clt/__init__.py
atlas_consortia_clt/sennet_clt/__init__.py
atlas_consortia_clt-1.0.4.dist-info/METADATA
atlas_consortia_clt-1.0.4.dist-info/WHEEL
atlas_consortia_clt-1.0.4.dist-info/entry_points.txt
atlas_consortia_clt-1.0.4.dist-info/top_level.txt
atlas_consortia_clt-1.0.4.dist-info/RECORD
