Metadata-Version: 2.4
Name: atlas-consortia-clt
Version: 1.0.4
Summary: HuBMAP and SenNet command-line interface to download data using a manifest file.
Author-email: Atlas Consortia <api-developers@hubmapconsortium.org>
License: MIT
Project-URL: Homepage, https://github.com/x-atlas-consortia/clt
Project-URL: Bug Tracker, https://github.com/x-atlas-consortia/clt/issues
Keywords: HuBMAP CLT,SenNet CLT,HuBMAP,SenNet,CLT,Command Line Transfer,Manifest
Classifier: Programming Language :: Python :: 3
Classifier: License :: OSI Approved :: MIT License
Classifier: Operating System :: OS Independent
Requires-Python: >=3.6
Requires-Dist: certifi>=2021.10.8
Requires-Dist: charset-normalizer>=2.0.10
Requires-Dist: idna>=3.3
Requires-Dist: requests>=2.27.1
Requires-Dist: urllib3<2.0,>=1.26.8
Requires-Dist: globus-cli>=3.1.4
